remsol-0.1.3.dist-info/METADATA
remsol-0.1.3.dist-info/WHEEL
remsol-0.1.3.dist-info/licenses/LICENSE
remsol/__init__.py
remsol/__init__.pyi
remsol/py.typed
remsol/remsol.pypy310-pp73-ppc_64-linux-gnu.so
remsol-0.1.3.dist-info/RECORD
