Metadata-Version: 2.4
Name: remsol
Version: 0.1.3
Classifier: Programming Language :: Rust
Classifier: Programming Language :: Python :: Implementation :: CPython
Classifier: Programming Language :: Python :: Implementation :: PyPy
License-File: LICENSE
Summary: Electromagnetic mode solver for 1D multilayer structures
Home-Page: https://github.com/mpasson/REMSOL
License: MIT
Requires-Python: >=3.10
